oppen_pretty_printer
