Metadata-Version: 2.1
Name: oppen-pretty-printer
Version: 0.1.2
Summary: pretty-printing algorithm developed by DEREK C. OPPEN
Home-page: https://github.com/stevej2608/oppen-pretty-printer
Author: Steve Jones
Author-email: jonesst608@gmail.com
License: MIT
Platform: UNKNOWN
Classifier: Development Status :: 2 - Pre-Alpha
Classifier: License :: OSI Approved :: MIT License
Classifier: Programming Language :: Python
Classifier: Programming Language :: Python :: 3.6
Classifier: Programming Language :: Python :: 3.7
